wapp/__init__.py
wapp-0.1.dist-info/LICENSE.txt
wapp-0.1.dist-info/METADATA
wapp-0.1.dist-info/WHEEL
wapp-0.1.dist-info/top_level.txt
wapp-0.1.dist-info/RECORD
